README.md
setup.cfg
setup.py
EnjoyAPI/EnjoyAPI.py
EnjoyAPI/__init__.py
EnjoyAPI.egg-info/PKG-INFO
EnjoyAPI.egg-info/SOURCES.txt
EnjoyAPI.egg-info/dependency_links.txt
EnjoyAPI.egg-info/requires.txt
EnjoyAPI.egg-info/top_level.txt