Metadata-Version: 1.0
Name: EnjoyAPI
Version: 1.0
Summary: Enjoy API wrapper
Home-page: https://github.com/KotypeyPyEdition/EnjoyAPI
Author: Kotypey
Author-email: Kotypey@gmail.com
License: UNKNOWN
Platform: UNKNOWN
